metagenompy/__init__.py
metagenompy/data.py
metagenompy/example_data/__init__.py
metagenompy/example_data/blast_result.csv.gz
metagenompy/taxonomy.py
metagenompy/visualization.py
metagenompy-0.4.6.dist-info/LICENSE
metagenompy-0.4.6.dist-info/WHEEL
metagenompy-0.4.6.dist-info/METADATA
metagenompy-0.4.6.dist-info/RECORD
