Metadata-Version: 2.1
Name: metagenompy
Version: 0.4.6
Summary: Your all-inclusive package for aggregating and visualizing metagenomic BLAST results.
Home-page: https://github.com/kpj/metagenompy
License: MIT
Author: kpj
Author-email: kim.philipp.jablonski@gmail.com
Requires-Python: >=3.7.1,<4.0.0
Classifier: License :: OSI Approved :: MIT License
Classifier: Programming Language :: Python :: 3
Classifier: Programming Language :: Python :: 3.8
Classifier: Programming Language :: Python :: 3.9
Requires-Dist: matplotlib (>=3.5.1,<4.0.0)
Requires-Dist: networkx (>=2.6.3,<3.0.0)
Requires-Dist: numpy (>=1.21.1,<2.0.0)
Requires-Dist: pandas (>=1.3.5,<2.0.0)
Requires-Dist: pygraphviz (>=1.7,<2.0)
Requires-Dist: seaborn (>=0.11.2,<0.12.0)
Requires-Dist: tqdm (>=4.62.3,<5.0.0)
Project-URL: Repository, https://github.com/kpj/metagenompy
